pyaudius/__init__.py
pyaudius/api/__init__.py
pyaudius/api/challenges_api.py
pyaudius/api/comments_api.py
pyaudius/api/dashboard_wallet_users_api.py
pyaudius/api/developer_apps_api.py
pyaudius/api/playlists_api.py
pyaudius/api/resolve_api.py
pyaudius/api/tips_api.py
pyaudius/api/tracks_api.py
pyaudius/api/users_api.py
pyaudius/api_client.py
pyaudius/api_response.py
pyaudius/configuration.py
pyaudius/exceptions.py
pyaudius/models/__init__.py
pyaudius/models/access.py
pyaudius/models/access_info_response.py
pyaudius/models/activity.py
pyaudius/models/albums_response.py
pyaudius/models/authorized_app.py
pyaudius/models/authorized_apps.py
pyaudius/models/blob_info.py
pyaudius/models/challenge_response.py
pyaudius/models/collection_activity.py
pyaudius/models/comment.py
pyaudius/models/comment_mention.py
pyaudius/models/comment_notification_setting.py
pyaudius/models/comment_response.py
pyaudius/models/connected_wallets.py
pyaudius/models/connected_wallets_response.py
pyaudius/models/cover_photo.py
pyaudius/models/dashboard_wallet_user.py
pyaudius/models/dashboard_wallet_users_response.py
pyaudius/models/decoded_user_token.py
pyaudius/models/developer_app.py
pyaudius/models/developer_app_response.py
pyaudius/models/developer_apps.py
pyaudius/models/encoded_user_id.py
pyaudius/models/extended_payment_split.py
pyaudius/models/extended_purchase_gate.py
pyaudius/models/extended_usdc_gate.py
pyaudius/models/favorite.py
pyaudius/models/favorites_response.py
pyaudius/models/follow_gate.py
pyaudius/models/followers_response.py
pyaudius/models/following_response.py
pyaudius/models/get_challenges.py
pyaudius/models/get_supported_users.py
pyaudius/models/get_supporters.py
pyaudius/models/get_tips_response.py
pyaudius/models/nft_collection.py
pyaudius/models/nft_gate.py
pyaudius/models/playlist.py
pyaudius/models/playlist_added_timestamp.py
pyaudius/models/playlist_artwork.py
pyaudius/models/playlist_response.py
pyaudius/models/playlist_search_result.py
pyaudius-0.1.2.dist-info/METADATA
pyaudius-0.1.2.dist-info/WHEEL
pyaudius-0.1.2.dist-info/RECORD
