Metadata-Version: 2.1
Name: pyaudius
Version: 0.1.2
Summary: A Python Implentation of the Audius API
Home-page: https://github.com/samgutentag/pyaudius
License: NoLicense
Keywords: music,audius,API,web3,crypto
Author: Sam Gutentag
Author-email: sam@gutentag.dev
Requires-Python: >=3.8,<4.0
Classifier: License :: Other/Proprietary License
Classifier: Programming Language :: Python :: 3
Classifier: Programming Language :: Python :: 3.8
Classifier: Programming Language :: Python :: 3.9
Classifier: Programming Language :: Python :: 3.10
Classifier: Programming Language :: Python :: 3.11
Classifier: Programming Language :: Python :: 3.12
Classifier: Programming Language :: Python :: 3.13
Requires-Dist: pydantic (>=2)
Requires-Dist: python-dateutil (>=2.8.2)
Requires-Dist: typing-extensions (>=4.7.1)
Requires-Dist: urllib3 (>=1.25.3,<3.0.0)
Project-URL: Repository, https://github.com/samgutentag/pyaudius
